Metadata-Version: 1.0
Name: bookpy
Version: 0.1.2
Summary: A cli tool for rename your e-books.
Home-page: https://github.com/stsewd/bookpy
Author: Santos Gallegos
Author-email: santos_g@outlook.com
License: MIT
Platform: UNKNOWN
